srupy/__init__.py
srupy/app.py
srupy/iterator.py
srupy/models.py
srupy/response.py
srupy/sruexceptions.py
srupy/util.py
srupy-0.1.1.dist-info/LICENSE.md
srupy-0.1.1.dist-info/WHEEL
srupy-0.1.1.dist-info/METADATA
srupy-0.1.1.dist-info/RECORD
