Metadata-Version: 2.1
Name: srupy
Version: 0.1.1
Summary: A Python client for fetching data from SRU endpoints
License: MIT
Author: Andreas Lüschow
Requires-Python: >=3.7,<4.0
Classifier: License :: OSI Approved :: MIT License
Classifier: Programming Language :: Python :: 3
Classifier: Programming Language :: Python :: 3.7
Classifier: Programming Language :: Python :: 3.8
Requires-Dist: lxml (>=4.5.2,<5.0.0)
Requires-Dist: requests (>=2.24.0,<3.0.0)
